{
 "date": "20260706",
 "suspects": {
  "011230": {
   "name": "삼화전자",
   "sector": "삼화전자",
   "entry": 3780.0,
   "score": 0,
   "breakdown": {},
   "suspicion_score": 72,
   "score_breakdown_display": {},
   "rank": 1,
   "change_pct": 5.73,
   "change_basis": "KRX",
   "high_pct": 20.84,
   "pattern": "shakeout",
   "prime": false,
   "theme": "",
   "value_eok": 398,
   "turnover_pct": 100.9,
   "peak_turnover_pct": null,
   "turnover_basis": "float",
   "turnover_metric": "vol_float",
   "theme_leader": false,
   "spark_max_x": null,
   "mega_flow": false,
   "flow_today_buy": false,
   "deep_shake": null,
   "visible_experimental": true,
   "reaccum": null,
   "reignition": null,
   "geupso": false,
   "geupso_bars": [],
   "low_accum": false,
   "low_accum_bars": [],
   "alert_now": null,
   "alert_release": null,
   "shakeout": true,
   "fade_pct": 15.1,
   "tp_hint": "+7~10% (12% 천장 실측)",
   "forecast": null,
   "matched_events": [],
   "first_seen": "2026-07-06 11:05:07 KST",
   "evaluated": false,
   "result": null,
   "final": false
  }
 },
 "as_of": "2026-07-06 11:54:53 KST"
}