{
  "as_of": "2026-06-11 09:07 KST",
  "intraday_rank": [
    {
      "ticker": "라이콤",
      "code": "388790",
      "tomorrow_up_prob": "72%",
      "entry": 7860.0,
      "target": 8253,
      "stop": 7624,
      "confidence": "상",
      "reasons": [
        "강세마감(0.95)",
        "MACD강세",
        "RSI65.8 강세"
      ],
      "risk": "특이 위험 낮음",
      "day_change": null,
      "cause_news": [
        {
          "title": "[특징주] 라이콤, AI데이터센터 수주 확대에 방산까지 \"광통신 수혜주로...",
          "url": "https://www.widedaily.com/news/articleView.html?idxno=295152",
          "office": "widedaily",
          "sentiment": "호재",
          "cause_score": 11,
          "cause_reason": "제목 언급, 주어, 원인표현, 인과표현, 재료, 검색맥락, 오래됨"
        },
        {
          "title": "라이콤, AI 데이터센터·방산 수혜 기대감에 19%↑[특징주]",
          "url": "https://www.edaily.co.kr/news/newspath.asp?newsid=03270166645478768",
          "office": "edaily",
          "sentiment": "호재",
          "cause_score": 11,
          "cause_reason": "제목 언급, 주어, 원인표현, 인과표현, 재료, 검색맥락, 오래됨"
        },
        {
          "title": "[시간외Y] 라이콤, E8, 하이로닉 '상한가'",
          "url": "http://www.newsprime.co.kr/news/article.html?no=736137",
          "office": "newsprime",
          "sentiment": "호재",
          "cause_score": 9,
          "cause_reason": "제목 언급, 주어, 원인표현, 검색맥락"
        }
      ],
      "cause_confidence": "높음",
      "cause_summary": "[특징주] 라이콤, AI데이터센터 수주 확대에 방산까지 \"광통신 수혜주로..."
    },
    {
      "ticker": "SK이터닉스",
      "code": "475150",
      "tomorrow_up_prob": "64%",
      "entry": 53900.0,
      "target": 56595,
      "stop": 52283,
      "confidence": "중",
      "reasons": [
        "강세마감(1.0)",
        "MACD강세",
        "RSI63.2 강세"
      ],
      "risk": "특이 위험 낮음",
      "day_change": null,
      "cause_news": [
        {
          "title": "[급등락주 짚어보기] SK이터닉스, SK그룹 신재생에너지 재편 기대에 ‘...",
          "url": "https://www.etoday.co.kr/news/view/2592365",
          "office": "etoday",
          "sentiment": "호재",
          "cause_score": 11,
          "cause_reason": "제목 언급, 주어, 원인표현, 검색맥락, 당일"
        },
        {
          "title": "KKR과 신재생사업 빅딜…SK이터닉스 '상한가'",
          "url": "https://www.hankyung.com/article/2026061090251",
          "office": "hankyung",
          "sentiment": "악재",
          "cause_score": 6,
          "cause_reason": "제목 언급, 원인표현, 검색맥락, 악재, 당일"
        }
      ],
      "cause_confidence": "높음",
      "cause_summary": "[급등락주 짚어보기] SK이터닉스, SK그룹 신재생에너지 재편 기대에 ‘..."
    },
    {
      "ticker": "케이뱅크",
      "code": "279570",
      "tomorrow_up_prob": "62%",
      "entry": 6100.0,
      "target": 6405,
      "stop": 5917,
      "confidence": "중",
      "reasons": [
        "강세마감(0.7)",
        "RSI58.8 강세",
        "호재"
      ],
      "risk": "특이 위험 낮음",
      "day_change": 4.33,
      "cause_news": [
        {
          "title": "제주은행 23% 급등 이어 케이뱅크 4% 상승",
          "url": "http://www.econonews.co.kr/news/articleView.html?idxno=439516",
          "office": "econonews",
          "sentiment": "호재",
          "cause_score": 9,
          "cause_reason": "제목 언급, 원인표현, 검색맥락, 당일"
        },
        {
          "title": "케이뱅크 주가, 강세... 외인·기관 쌍끌이 매수",
          "url": "https://www.ggilbo.com/news/articleView.html?idxno=1162859",
          "office": "ggilbo",
          "sentiment": "악재",
          "cause_score": 8,
          "cause_reason": "제목 언급, 주어, 원인표현, 검색맥락, 악재, 당일"
        }
      ],
      "cause_confidence": "높음",
      "cause_summary": "제주은행 23% 급등 이어 케이뱅크 4% 상승"
    },
    {
      "ticker": "제주은행",
      "code": "006220",
      "tomorrow_up_prob": "62%",
      "entry": 13760.0,
      "target": 14448,
      "stop": 13347,
      "confidence": "중",
      "reasons": [
        "강세마감(0.79)",
        "RSI69.3 강세",
        "호재"
      ],
      "risk": "특이 위험 낮음",
      "day_change": null,
      "cause_news": [
        {
          "title": "제주은행 23% 급등 이어 케이뱅크 4% 상승",
          "url": "http://www.econonews.co.kr/news/articleView.html?idxno=439516",
          "office": "econonews",
          "sentiment": "호재",
          "cause_score": 13,
          "cause_reason": "제목 언급, 주어, 원인표현, 재료, 검색맥락, 당일"
        }
      ],
      "cause_confidence": "높음",
      "cause_summary": "제주은행 23% 급등 이어 케이뱅크 4% 상승"
    },
    {
      "ticker": "테스",
      "code": "095610",
      "tomorrow_up_prob": "61%",
      "entry": 173000.0,
      "target": 181650,
      "stop": 167810,
      "confidence": "중",
      "reasons": [
        "정배열",
        "MACD강세",
        "일목 구름위"
      ],
      "risk": "약한 마감, Stoch 과매수",
      "day_change": 7.43,
      "cause_news": [
        {
          "title": "[특징주] 테스, 'HBM4 수율 핵심' BSD 수주 기대감에 12%↑",
          "url": "http://www.newsdream.kr/news/articleView.html?idxno=112834",
          "office": "newsdream",
          "sentiment": "호재",
          "cause_score": 17,
          "cause_reason": "제목 언급, 주어, 원인표현, 인과표현, 재료, 검색맥락, 당일"
        },
        {
          "title": "테스, 투자주의종목→투자경고종목 지정 예고",
          "url": "https://www.topstarnews.net/news/articleView.html?idxno=16086752",
          "office": "topstarnews",
          "sentiment": "호재",
          "cause_score": 7,
          "cause_reason": "제목 언급, 주어, 재료, 일반뉴스, 당일"
        }
      ],
      "cause_confidence": "높음",
      "cause_summary": "[특징주] 테스, 'HBM4 수율 핵심' BSD 수주 기대감에 12%↑"
    },
    {
      "ticker": "HD현대에너지솔루션",
      "code": "322000",
      "tomorrow_up_prob": "58%",
      "entry": 157400.0,
      "target": 165270,
      "stop": 152678,
      "confidence": "중",
      "reasons": [
        "강세마감(0.76)",
        "호재"
      ],
      "risk": "특이 위험 낮음",
      "day_change": null,
      "cause_news": [
        {
          "title": "[특징주] HD현대에너지솔루션, 재생에너지 100GW 확대 기대에 美 호재 겹...",
          "url": "https://www.tokenpost.kr/news/economy/367599",
          "office": "tokenpost",
          "sentiment": "호재",
          "cause_score": 11,
          "cause_reason": "제목 언급, 주어, 원인표현, 검색맥락, 당일"
        }
      ],
      "cause_confidence": "높음",
      "cause_summary": "[특징주] HD현대에너지솔루션, 재생에너지 100GW 확대 기대에 美 호재 겹..."
    },
    {
      "ticker": "화신정공",
      "code": "126640",
      "tomorrow_up_prob": "53%",
      "entry": 5750.0,
      "target": 6038,
      "stop": 5578,
      "confidence": "하",
      "reasons": [
        "정배열",
        "MACD강세",
        "일목 구름위"
      ],
      "risk": "RSI93.4 과매수, Stoch 과매수",
      "day_change": null,
      "cause_news": [
        {
          "title": "화신정공, 투자경고종목 지정→추가 상승 시 거래정지 가능",
          "url": "https://www.topstarnews.net/news/articleView.html?idxno=16086730",
          "office": "topstarnews",
          "sentiment": "호재",
          "cause_score": 7,
          "cause_reason": "제목 언급, 주어, 재료, 일반뉴스, 당일"
        }
      ],
      "cause_confidence": "중간",
      "cause_summary": "화신정공, 투자경고종목 지정→추가 상승 시 거래정지 가능"
    }
  ],
  "closing_bet": [
    {
      "ticker": "라이콤",
      "code": "388790",
      "tomorrow_up_prob": "72%",
      "entry": 7860.0,
      "target": 8253,
      "stop": 7624,
      "confidence": "상",
      "reasons": [
        "강세마감(0.95)",
        "MACD강세",
        "RSI65.8 강세"
      ],
      "risk": "특이 위험 낮음",
      "day_change": null,
      "cause_news": [
        {
          "title": "[특징주] 라이콤, AI데이터센터 수주 확대에 방산까지 \"광통신 수혜주로...",
          "url": "https://www.widedaily.com/news/articleView.html?idxno=295152",
          "office": "widedaily",
          "sentiment": "호재",
          "cause_score": 11,
          "cause_reason": "제목 언급, 주어, 원인표현, 인과표현, 재료, 검색맥락, 오래됨"
        },
        {
          "title": "라이콤, AI 데이터센터·방산 수혜 기대감에 19%↑[특징주]",
          "url": "https://www.edaily.co.kr/news/newspath.asp?newsid=03270166645478768",
          "office": "edaily",
          "sentiment": "호재",
          "cause_score": 11,
          "cause_reason": "제목 언급, 주어, 원인표현, 인과표현, 재료, 검색맥락, 오래됨"
        },
        {
          "title": "[시간외Y] 라이콤, E8, 하이로닉 '상한가'",
          "url": "http://www.newsprime.co.kr/news/article.html?no=736137",
          "office": "newsprime",
          "sentiment": "호재",
          "cause_score": 9,
          "cause_reason": "제목 언급, 주어, 원인표현, 검색맥락"
        }
      ],
      "cause_confidence": "높음",
      "cause_summary": "[특징주] 라이콤, AI데이터센터 수주 확대에 방산까지 \"광통신 수혜주로..."
    },
    {
      "ticker": "SK이터닉스",
      "code": "475150",
      "tomorrow_up_prob": "64%",
      "entry": 53900.0,
      "target": 56595,
      "stop": 52283,
      "confidence": "중",
      "reasons": [
        "강세마감(1.0)",
        "MACD강세",
        "RSI63.2 강세"
      ],
      "risk": "특이 위험 낮음",
      "day_change": null,
      "cause_news": [
        {
          "title": "[급등락주 짚어보기] SK이터닉스, SK그룹 신재생에너지 재편 기대에 ‘...",
          "url": "https://www.etoday.co.kr/news/view/2592365",
          "office": "etoday",
          "sentiment": "호재",
          "cause_score": 11,
          "cause_reason": "제목 언급, 주어, 원인표현, 검색맥락, 당일"
        },
        {
          "title": "KKR과 신재생사업 빅딜…SK이터닉스 '상한가'",
          "url": "https://www.hankyung.com/article/2026061090251",
          "office": "hankyung",
          "sentiment": "악재",
          "cause_score": 6,
          "cause_reason": "제목 언급, 원인표현, 검색맥락, 악재, 당일"
        }
      ],
      "cause_confidence": "높음",
      "cause_summary": "[급등락주 짚어보기] SK이터닉스, SK그룹 신재생에너지 재편 기대에 ‘..."
    },
    {
      "ticker": "케이뱅크",
      "code": "279570",
      "tomorrow_up_prob": "62%",
      "entry": 6100.0,
      "target": 6405,
      "stop": 5917,
      "confidence": "중",
      "reasons": [
        "강세마감(0.7)",
        "RSI58.8 강세",
        "호재"
      ],
      "risk": "특이 위험 낮음",
      "day_change": 4.33,
      "cause_news": [
        {
          "title": "제주은행 23% 급등 이어 케이뱅크 4% 상승",
          "url": "http://www.econonews.co.kr/news/articleView.html?idxno=439516",
          "office": "econonews",
          "sentiment": "호재",
          "cause_score": 9,
          "cause_reason": "제목 언급, 원인표현, 검색맥락, 당일"
        },
        {
          "title": "케이뱅크 주가, 강세... 외인·기관 쌍끌이 매수",
          "url": "https://www.ggilbo.com/news/articleView.html?idxno=1162859",
          "office": "ggilbo",
          "sentiment": "악재",
          "cause_score": 8,
          "cause_reason": "제목 언급, 주어, 원인표현, 검색맥락, 악재, 당일"
        }
      ],
      "cause_confidence": "높음",
      "cause_summary": "제주은행 23% 급등 이어 케이뱅크 4% 상승"
    },
    {
      "ticker": "제주은행",
      "code": "006220",
      "tomorrow_up_prob": "62%",
      "entry": 13760.0,
      "target": 14448,
      "stop": 13347,
      "confidence": "중",
      "reasons": [
        "강세마감(0.79)",
        "RSI69.3 강세",
        "호재"
      ],
      "risk": "특이 위험 낮음",
      "day_change": null,
      "cause_news": [
        {
          "title": "제주은행 23% 급등 이어 케이뱅크 4% 상승",
          "url": "http://www.econonews.co.kr/news/articleView.html?idxno=439516",
          "office": "econonews",
          "sentiment": "호재",
          "cause_score": 13,
          "cause_reason": "제목 언급, 주어, 원인표현, 재료, 검색맥락, 당일"
        }
      ],
      "cause_confidence": "높음",
      "cause_summary": "제주은행 23% 급등 이어 케이뱅크 4% 상승"
    },
    {
      "ticker": "테스",
      "code": "095610",
      "tomorrow_up_prob": "61%",
      "entry": 173000.0,
      "target": 181650,
      "stop": 167810,
      "confidence": "중",
      "reasons": [
        "정배열",
        "MACD강세",
        "일목 구름위"
      ],
      "risk": "약한 마감, Stoch 과매수",
      "day_change": 7.43,
      "cause_news": [
        {
          "title": "[특징주] 테스, 'HBM4 수율 핵심' BSD 수주 기대감에 12%↑",
          "url": "http://www.newsdream.kr/news/articleView.html?idxno=112834",
          "office": "newsdream",
          "sentiment": "호재",
          "cause_score": 17,
          "cause_reason": "제목 언급, 주어, 원인표현, 인과표현, 재료, 검색맥락, 당일"
        },
        {
          "title": "테스, 투자주의종목→투자경고종목 지정 예고",
          "url": "https://www.topstarnews.net/news/articleView.html?idxno=16086752",
          "office": "topstarnews",
          "sentiment": "호재",
          "cause_score": 7,
          "cause_reason": "제목 언급, 주어, 재료, 일반뉴스, 당일"
        }
      ],
      "cause_confidence": "높음",
      "cause_summary": "[특징주] 테스, 'HBM4 수율 핵심' BSD 수주 기대감에 12%↑"
    }
  ],
  "disclaimer": "예측·투자 참고용이며 매수 추천이 아닙니다. 갭 리스크가 있으니 손절을 지키세요.",
  "backtest": {
    "sample": 30,
    "recent_hit_rate": "37% (n=30)",
    "avg_return": -3.06,
    "target_rate": "57%"
  }
}