{
 "generated_at": "2026-07-13 20:43:40 KST",
 "market_session": "closed",
 "disclaimer": "본 정보는 투자 참고용이며 매수 추천이 아닙니다. 투자 판단과 책임은 본인에게 있습니다.",
 "params": {
  "market": "UN",
  "reignition_body_pct": 1.5,
  "reignition_span_min": 5,
  "reignition_min_count": 2,
  "reignition_start": "1430",
  "reaccum_change_min": -5.0,
  "reaccum_change_max": 7.0,
  "reaccum_enabled": true,
  "reaccum_visible": true,
  "reaccum_max": 12,
  "explosion_vol_turnover": 90.0,
  "explosion_high_pct": 22.0,
  "explosion_window": 6,
  "explosion_scan_n": 50,
  "youtong_change_pct": 7.0,
  "youtong_turnover_min": 50.0,
  "youtong_start": "0930",
  "youtong_spark_min": 1,
  "geupso_body_pct": 2.0,
  "geupso_min_count": 2,
  "geupso_change_max": 10.0,
  "reaccum_track_days": 30,
  "lowaccum_change_max": -10.0,
  "lowaccum_body_pct": 2.0,
  "lowaccum_min_count": 3,
  "telegram_seed": true,
  "telegram_channel": "FastStockNews"
 },
 "universe_count": 45,
 "events": [
  {
   "id": "2026-07-14_미국 CPI 발표 (6",
   "date": "2026-07-14",
   "dday": 1,
   "title": "미국 CPI 발표 (6월분)",
   "category": [
    "금리",
    "환율"
   ],
   "importance": 9,
   "country": "US",
   "estimated": true
  }
 ],
 "explosions": [
  {
   "code": "006660",
   "name": "삼성공조",
   "sector": "삼성공조",
   "high_pct": 24.89,
   "vol_turnover_pct": 101.6,
   "value_eok": 433,
   "price": 10080.0,
   "change_pct": 5.88,
   "backfill": false
  },
  {
   "code": "005360",
   "name": "모나미",
   "sector": "모나미",
   "high_pct": 29.6,
   "vol_turnover_pct": 118.8,
   "value_eok": 402,
   "price": 2040.0,
   "change_pct": -4.9,
   "backfill": true
  },
  {
   "code": "037070",
   "name": "파세코",
   "sector": "파세코",
   "high_pct": 28.76,
   "vol_turnover_pct": 207.4,
   "value_eok": 1004,
   "price": 8760.0,
   "change_pct": 25.32,
   "backfill": false
  },
  {
   "code": "003680",
   "name": "한성기업",
   "sector": "한성기업",
   "high_pct": 29.91,
   "vol_turnover_pct": 340.4,
   "value_eok": 1121,
   "price": 9300.0,
   "change_pct": 9.93,
   "backfill": false
  }
 ],
 "youtong": [
  {
   "code": "003680",
   "name": "한성기업",
   "sector": "한성기업",
   "change_pct": 9.93,
   "high_pct": 29.91,
   "vol_turnover_pct": 340.4,
   "value_eok": 1121,
   "price": 9300.0,
   "first_seen": "09:52",
   "exploded": true
  },
  {
   "code": "037070",
   "name": "파세코",
   "sector": "파세코",
   "change_pct": 25.32,
   "high_pct": 28.76,
   "vol_turnover_pct": 207.4,
   "value_eok": 1004,
   "price": 8760.0,
   "first_seen": "09:42",
   "exploded": true
  },
  {
   "code": "024060",
   "name": "흥구석유",
   "sector": "흥구석유",
   "change_pct": 7.38,
   "high_pct": 17.71,
   "vol_turnover_pct": 138.3,
   "value_eok": 1704,
   "price": 11640.0,
   "first_seen": "10:42",
   "exploded": false
  },
  {
   "code": "005360",
   "name": "모나미",
   "sector": "모나미",
   "change_pct": -4.9,
   "high_pct": 29.6,
   "vol_turnover_pct": 118.8,
   "value_eok": 402,
   "price": 2040.0,
   "first_seen": "10:32",
   "exploded": true
  },
  {
   "code": "006660",
   "name": "삼성공조",
   "sector": "삼성공조",
   "change_pct": 5.88,
   "high_pct": 24.89,
   "vol_turnover_pct": 101.6,
   "value_eok": 433,
   "price": 10080.0,
   "first_seen": "12:42",
   "exploded": true
  },
  {
   "code": "413630",
   "name": "씨피시스템",
   "sector": "씨피시스템",
   "change_pct": 10.6,
   "high_pct": 27.88,
   "vol_turnover_pct": 82.8,
   "value_eok": 216,
   "price": 2400.0,
   "first_seen": "12:52",
   "exploded": false
  },
  {
   "code": "042110",
   "name": "에스씨디",
   "sector": "에스씨디",
   "change_pct": 13.13,
   "high_pct": 28.89,
   "vol_turnover_pct": 82.8,
   "value_eok": 254,
   "price": 1249.0,
   "first_seen": "14:22",
   "exploded": false
  },
  {
   "code": "002700",
   "name": "신일전자",
   "sector": "신일전자",
   "change_pct": 9.83,
   "high_pct": 26.84,
   "vol_turnover_pct": 80.7,
   "value_eok": 564,
   "price": 1195.0,
   "first_seen": "13:02",
   "exploded": false
  },
  {
   "code": "069540",
   "name": "빛과전자",
   "sector": "빛과전자",
   "change_pct": -1.51,
   "high_pct": 23.44,
   "vol_turnover_pct": 55.5,
   "value_eok": 929,
   "price": 2290.0,
   "first_seen": "12:42",
   "exploded": false
  },
  {
   "code": "079650",
   "name": "서산",
   "sector": "서산",
   "change_pct": 0.54,
   "high_pct": 15.77,
   "vol_turnover_pct": 53.1,
   "value_eok": 203,
   "price": 5610.0,
   "first_seen": "10:32",
   "exploded": false
  }
 ],
 "suspects": [
  {
   "code": "001210",
   "name": "금호전기",
   "sector": "금호전기",
   "pattern": "reaccum",
   "geupso": false,
   "geupso_bars": [
    {
     "time": "14:40",
     "body_pct": 3.23
    }
   ],
   "shake": null,
   "deep_shake": null,
   "suspicion_score": 78,
   "calibrated_prob": null,
   "score_breakdown": {
    "base": 62,
    "re_count": 0,
    "re_body": 2,
    "peak_turnover": 10,
    "re_turnover": 4
   },
   "score_raw": 0,
   "score_breakdown_raw": {
    "base": 0,
    "re_count": 0,
    "re_body": 0,
    "peak_turnover": 0,
    "re_turnover": 0
   },
   "forecast": {
    "horizon": "3일 내 +7%",
    "prob_pct": 46,
    "base_pct": 46,
    "strong": false,
    "next_day_7_pct": 25,
    "note": "과거 실측 확률·보장 아님"
   },
   "price": 1015.0,
   "change_pct": -23.74,
   "change_basis": "KRX",
   "high_pct": 3.61,
   "value_eok": 349,
   "snapshot_open": 1300.0,
   "snapshot_high": 1379.0,
   "snapshot_low": 984.0,
   "snapshot_close": 1015.0,
   "snapshot_volume": 30190449.0,
   "snapshot_value": 34943000000.0,
   "snapshot_value_eok": 349.4,
   "snapshot_as_of": "20260713",
   "signal_date": "20260713",
   "signal_open": 1300.0,
   "signal_high": 1379.0,
   "signal_low": 984.0,
   "signal_close": 1015.0,
   "signal_prev_close": 1331.0,
   "signal_volume": 30190449.0,
   "signal_value": 34943000000.0,
   "signal_value_eok": 349.4,
   "signal_source": "daily_latest",
   "turnover_pct": 73.9,
   "peak_turnover_pct": 329.9,
   "float_ratio": 0.66,
   "turnover_basis": "float",
   "ma10": 1121.6,
   "ma10_margin_pct": -9.5,
   "spark": {
    "clusters": []
   },
   "spark_max_x": null,
   "spark_max_pct": null,
   "mega_flow": false,
   "reignition": {
    "body_pct": 3.23,
    "time": "14:40",
    "value_eok": 7,
    "count": 1
   },
   "reignition_bars": [
    {
     "time": "14:40",
     "body_pct": 3.23,
     "value_eok": 7
    }
   ],
   "low_accum": true,
   "low_accum_bars": [
    {
     "time": "09:00",
     "body_pct": 4.38
    },
    {
     "time": "09:35",
     "body_pct": 2.65
    },
    {
     "time": "09:45",
     "body_pct": 3.17
    },
    {
     "time": "12:20",
     "body_pct": 3.29
    },
    {
     "time": "13:25",
     "body_pct": 3.9
    },
    {
     "time": "14:10",
     "body_pct": 6.24
    },
    {
     "time": "14:20",
     "body_pct": 6.77
    },
    {
     "time": "14:40",
     "body_pct": 3.23
    }
   ],
   "news": [],
   "matched_events": [
    {
     "id": "2026-07-14_미국 CPI 발표 (6",
     "title": "미국 CPI 발표 (6월분)",
     "dday": 1,
     "categories": [
      "금리"
     ],
     "score": 4.9
    }
   ],
   "theme": "반도체",
   "material": {
    "grade": "N",
    "score": 0,
    "summary": "",
    "sentiment": "중립",
    "reliability": "뉴스없음",
    "freshness": "미확인",
    "directness": "미확인",
    "tags": [],
    "risk_flags": [],
    "evidence": [],
    "source_count": 0,
    "relevant_count": 0
   },
   "visible_experimental": true,
   "reaccum": {
    "peak_date": "20260709",
    "peak_value_eok": 1866,
    "peak_high_pct": 25.04,
    "peak_turnover_pct": 329.9,
    "peak_ibs": 0.38,
    "peak_uppertail": 23.7,
    "ma20": 865.6,
    "ma20_margin_pct": 17.26,
    "cause_summary": "“호남하면 이 그룹이었는데” ‘금호’ 이름으로 30% 급등…모조리 ...",
    "was_theme_leader": false,
    "source": "live"
   },
   "leader_cohort_prob": null,
   "alert_now": "경고",
   "alert_release": false,
   "alert_release_rule": {
    "source": "KRX_KOSCOM",
    "retrieved_via": "NAVER_FINANCE_NOTICE",
    "notice_date": "20260629",
    "designation_date": "20260630",
    "first_review_date_notice": "20260713",
    "first_review_date_adjusted": "20260713",
    "threshold_5d_pct": 60.0,
    "threshold_15d_pct": 100.0,
    "recent_high_window": 15,
    "min_elapsed_days": 10,
    "logic_version": "krx-release-v2",
    "parse_status": "ok",
    "source_url": "https://finance.naver.com/item/news_notice_read.naver?no=48443410&code=001210&page_notice=1",
    "raw_text_hash": "9c922ea27b4b7e4e1d2a",
    "fetched_at": "2026-07-13 20:43:35 KST",
    "notice_no": "48443410"
   },
   "alert_release_checks": {
    "as_of_date": "20260713",
    "elapsed_days": 10,
    "elapsed_ok": true,
    "five_day_ok": true,
    "fifteen_day_ok": false,
    "not_recent_high_ok": true,
    "halt_days_excluded": [],
    "current_price": 1015.0,
    "t_minus_5_close": 963.0,
    "t_minus_15_close": 485.0
   },
   "alert_release_error": null,
   "alert_elapsed_days": 10,
   "alert_risk_released": false,
   "rank_bucket": 2,
   "rank_reason": "저점매집+폭발회전 330% → bucket 2",
   "shadow_bucket": [
    "S1",
    "S2"
   ],
   "expected_touch7_rate": 86.7,
   "expected_high_pct": 17.0,
   "rank_bucket_stats_snapshot": {
    "label": "저점매집+회전90",
    "n": 15,
    "unique_n": 13,
    "touch7_rate": 86.7,
    "expected_high_pct": 17.0,
    "avg_return": 9.09,
    "bucket": 2,
    "basis": "정렬4.md 2026-07-10 확정 스냅샷",
    "population": "overlapping_retro_reference"
   },
   "rank_prior": {
    "source": "chairman_40y_rule",
    "strength": "strong",
    "summary": "저점매집과 폭발일 회전율 90% 이상"
   },
   "rank_policy_name": "rank4",
   "rank_model_version": "rank4-v1",
   "rank_model_source_commit": "7f3acab",
   "rank_model_effective_from": "20260713",
   "rank_model_effective_at": "2026-07-13 09:00:00 KST",
   "precut_rank": 1,
   "published": true,
   "published_rank": 1,
   "theme_leader": false,
   "rank_retro_stats": {
    "basis": "retro",
    "population": "all",
    "model_version": "rank4-v1",
    "n": 14,
    "unique_n": 12,
    "touch7_rate": 85.7,
    "wilson7_lower": 60.1,
    "avg_high_pct": 16.07,
    "median_high_pct": 14.75,
    "min_high_pct": 1.02,
    "valid": true
   },
   "rank_forward_stats": {
    "basis": "forward_saved_signal",
    "population": "eod",
    "model_version": "rank4-v1",
    "n": 0,
    "unique_n": 0,
    "touch7_rate": null,
    "wilson7_lower": null,
    "avg_high_pct": null,
    "median_high_pct": null,
    "min_high_pct": null,
    "valid": false
   }
  },
  {
   "code": "002990",
   "name": "금호건설",
   "sector": "금호건설",
   "pattern": "reaccum",
   "geupso": false,
   "geupso_bars": [
    {
     "time": "14:40",
     "body_pct": 2.75
    }
   ],
   "shake": null,
   "deep_shake": null,
   "suspicion_score": 72,
   "calibrated_prob": null,
   "score_breakdown": {
    "base": 62,
    "re_count": 2,
    "re_body": 2,
    "peak_turnover": 4,
    "re_turnover": 2
   },
   "score_raw": 0,
   "score_breakdown_raw": {
    "base": 0,
    "re_count": 0,
    "re_body": 0,
    "peak_turnover": 0,
    "re_turnover": 0
   },
   "forecast": {
    "horizon": "3일 내 +7%",
    "prob_pct": 52,
    "base_pct": 46,
    "strong": true,
    "next_day_7_pct": 25,
    "note": "과거 실측 확률·보장 아님"
   },
   "price": 13970.0,
   "change_pct": -16.94,
   "change_basis": "KRX",
   "high_pct": 1.13,
   "value_eok": 1695,
   "snapshot_open": 16030.0,
   "snapshot_high": 17010.0,
   "snapshot_low": 12600.0,
   "snapshot_close": 13970.0,
   "snapshot_volume": 11385860.0,
   "snapshot_value": 169516000000.0,
   "snapshot_value_eok": 1695.2,
   "snapshot_as_of": "20260713",
   "signal_date": "20260713",
   "signal_open": 16030.0,
   "signal_high": 17010.0,
   "signal_low": 12600.0,
   "signal_close": 13970.0,
   "signal_prev_close": 16820.0,
   "signal_volume": 11385860.0,
   "signal_value": 169516000000.0,
   "signal_value_eok": 1695.2,
   "signal_source": "daily_latest",
   "turnover_pct": 58.8,
   "peak_turnover_pct": 131.9,
   "float_ratio": 0.52,
   "turnover_basis": "float",
   "ma10": 13541.0,
   "ma10_margin_pct": 3.17,
   "spark": {
    "clusters": []
   },
   "spark_max_x": null,
   "spark_max_pct": null,
   "mega_flow": false,
   "reignition": {
    "body_pct": 2.75,
    "time": "14:40",
    "value_eok": 32,
    "count": 2
   },
   "reignition_bars": [
    {
     "time": "14:40",
     "body_pct": 2.75,
     "value_eok": 32
    },
    {
     "time": "15:15",
     "body_pct": 1.97,
     "value_eok": 22
    }
   ],
   "low_accum": true,
   "low_accum_bars": [
    {
     "time": "09:00",
     "body_pct": 4.68
    },
    {
     "time": "09:35",
     "body_pct": 2.03
    },
    {
     "time": "09:45",
     "body_pct": 2.01
    },
    {
     "time": "09:55",
     "body_pct": 2.77
    },
    {
     "time": "11:10",
     "body_pct": 3.06
    },
    {
     "time": "12:15",
     "body_pct": 2.9
    },
    {
     "time": "12:35",
     "body_pct": 2.27
    },
    {
     "time": "13:25",
     "body_pct": 3.96
    },
    {
     "time": "14:00",
     "body_pct": 3.11
    },
    {
     "time": "14:10",
     "body_pct": 7.67
    },
    {
     "time": "14:20",
     "body_pct": 9.21
    },
    {
     "time": "14:40",
     "body_pct": 2.75
    }
   ],
   "news": [],
   "matched_events": [
    {
     "id": "2026-07-14_미국 CPI 발표 (6",
     "title": "미국 CPI 발표 (6월분)",
     "dday": 1,
     "categories": [
      "금리"
     ],
     "score": 4.9
    }
   ],
   "theme": "금리",
   "material": {
    "grade": "B",
    "score": 65,
    "summary": "'반도체클러스터' 테마 여전히 뜨겁네…금호건설, 거래재개 후 13%↑",
    "sentiment": "중립",
    "reliability": "뉴스",
    "freshness": "미확인",
    "freshness_days": null,
    "directness": "간접",
    "tags": [
     "S급재료",
     "금리",
     "테마/수혜"
    ],
    "risk_flags": [],
    "evidence": [
     {
      "title": "'반도체클러스터' 테마 여전히 뜨겁네…금호건설, 거래재개 후 13%↑",
      "datetime": null,
      "source": "",
      "url": null,
      "score": 65
     }
    ],
    "source_count": 0,
    "relevant_count": 1
   },
   "visible_experimental": true,
   "reaccum": {
    "peak_date": "20260709",
    "peak_value_eok": 4164,
    "peak_high_pct": 28.57,
    "peak_turnover_pct": 131.9,
    "peak_ibs": 0.82,
    "peak_uppertail": 4.0,
    "ma20": 9277.2,
    "ma20_margin_pct": 50.58,
    "cause_summary": "'반도체클러스터' 테마 여전히 뜨겁네…금호건설, 거래재개 후 13%↑",
    "was_theme_leader": false,
    "source": "live"
   },
   "leader_cohort_prob": null,
   "alert_now": "경고",
   "alert_release": false,
   "alert_release_rule": {
    "source": "KRX_KOSCOM",
    "retrieved_via": "NAVER_FINANCE_NOTICE",
    "notice_date": "20260630",
    "designation_date": "20260701",
    "first_review_date_notice": "20260714",
    "first_review_date_adjusted": null,
    "threshold_5d_pct": 60.0,
    "threshold_15d_pct": 100.0,
    "recent_high_window": 15,
    "min_elapsed_days": 10,
    "logic_version": "krx-release-v2",
    "parse_status": "ok",
    "source_url": "https://finance.naver.com/item/news_notice_read.naver?no=49904863&code=002990&page_notice=2",
    "raw_text_hash": "e5deeb13f58a95f8c805",
    "fetched_at": "2026-07-13 20:43:34 KST",
    "notice_no": "49904863"
   },
   "alert_release_checks": {
    "as_of_date": "20260713",
    "elapsed_days": 8,
    "elapsed_ok": false,
    "five_day_ok": null,
    "fifteen_day_ok": null,
    "not_recent_high_ok": null,
    "halt_days_excluded": [
     "20260708"
    ]
   },
   "alert_release_error": null,
   "alert_elapsed_days": 8,
   "alert_risk_released": false,
   "rank_bucket": 2,
   "rank_reason": "저점매집+폭발회전 132% → bucket 2",
   "shadow_bucket": [
    "S2"
   ],
   "expected_touch7_rate": 86.7,
   "expected_high_pct": 17.0,
   "rank_bucket_stats_snapshot": {
    "label": "저점매집+회전90",
    "n": 15,
    "unique_n": 13,
    "touch7_rate": 86.7,
    "expected_high_pct": 17.0,
    "avg_return": 9.09,
    "bucket": 2,
    "basis": "정렬4.md 2026-07-10 확정 스냅샷",
    "population": "overlapping_retro_reference"
   },
   "rank_prior": {
    "source": "chairman_40y_rule",
    "strength": "strong",
    "summary": "저점매집과 폭발일 회전율 90% 이상"
   },
   "rank_policy_name": "rank4",
   "rank_model_version": "rank4-v1",
   "rank_model_source_commit": "7f3acab",
   "rank_model_effective_from": "20260713",
   "rank_model_effective_at": "2026-07-13 09:00:00 KST",
   "precut_rank": 2,
   "published": true,
   "published_rank": 2,
   "theme_leader": false,
   "rank_retro_stats": {
    "basis": "retro",
    "population": "all",
    "model_version": "rank4-v1",
    "n": 14,
    "unique_n": 12,
    "touch7_rate": 85.7,
    "wilson7_lower": 60.1,
    "avg_high_pct": 16.07,
    "median_high_pct": 14.75,
    "min_high_pct": 1.02,
    "valid": true
   },
   "rank_forward_stats": {
    "basis": "forward_saved_signal",
    "population": "eod",
    "model_version": "rank4-v1",
    "n": 0,
    "unique_n": 0,
    "touch7_rate": null,
    "wilson7_lower": null,
    "avg_high_pct": null,
    "median_high_pct": null,
    "min_high_pct": null,
    "valid": false
   }
  },
  {
   "code": "091590",
   "name": "남화토건",
   "sector": "남화토건",
   "pattern": "reaccum",
   "geupso": false,
   "geupso_bars": [
    {
     "time": "14:50",
     "body_pct": 2.55
    }
   ],
   "shake": null,
   "deep_shake": null,
   "suspicion_score": 71,
   "calibrated_prob": null,
   "score_breakdown": {
    "base": 62,
    "re_count": 4,
    "re_body": 1,
    "peak_turnover": 4,
    "re_turnover": 0
   },
   "score_raw": 0,
   "score_breakdown_raw": {
    "base": 0,
    "re_count": 0,
    "re_body": 0,
    "peak_turnover": 0,
    "re_turnover": 0
   },
   "forecast": {
    "horizon": "3일 내 +7%",
    "prob_pct": 46,
    "base_pct": 46,
    "strong": false,
    "next_day_7_pct": 25,
    "note": "과거 실측 확률·보장 아님"
   },
   "price": 7320.0,
   "change_pct": -17.85,
   "change_basis": "KRX",
   "high_pct": 0.11,
   "value_eok": 62,
   "snapshot_open": 8670.0,
   "snapshot_high": 8920.0,
   "snapshot_low": 7200.0,
   "snapshot_close": 7320.0,
   "snapshot_volume": 778127.0,
   "snapshot_value": 6242000000.0,
   "snapshot_value_eok": 62.4,
   "snapshot_as_of": "20260713",
   "signal_date": "20260713",
   "signal_open": 8670.0,
   "signal_high": 8920.0,
   "signal_low": 7200.0,
   "signal_close": 7320.0,
   "signal_prev_close": 8910.0,
   "signal_volume": 778127.0,
   "signal_value": 6242000000.0,
   "signal_value_eok": 62.4,
   "signal_source": "daily_latest",
   "turnover_pct": 16.1,
   "peak_turnover_pct": 137.2,
   "float_ratio": 0.4113,
   "turnover_basis": "float",
   "ma10": 9218.0,
   "ma10_margin_pct": -20.59,
   "spark": {
    "clusters": []
   },
   "spark_max_x": null,
   "spark_max_pct": null,
   "mega_flow": false,
   "reignition": {
    "body_pct": 2.55,
    "time": "14:50",
    "value_eok": 0,
    "count": 3
   },
   "reignition_bars": [
    {
     "time": "14:30",
     "body_pct": 1.59,
     "value_eok": 0
    },
    {
     "time": "14:50",
     "body_pct": 2.55,
     "value_eok": 0
    },
    {
     "time": "14:55",
     "body_pct": 1.71,
     "value_eok": 1
    }
   ],
   "low_accum": true,
   "low_accum_bars": [
    {
     "time": "09:10",
     "body_pct": 2.03
    },
    {
     "time": "09:20",
     "body_pct": 3.25
    },
    {
     "time": "14:10",
     "body_pct": 3.06
    },
    {
     "time": "14:20",
     "body_pct": 2.43
    },
    {
     "time": "14:50",
     "body_pct": 2.55
    }
   ],
   "news": [],
   "matched_events": [
    {
     "id": "2026-07-14_미국 CPI 발표 (6",
     "title": "미국 CPI 발표 (6월분)",
     "dday": 1,
     "categories": [
      "금리"
     ],
     "score": 7.4
    }
   ],
   "theme": "반도체",
   "material": {
    "grade": "N",
    "score": 0,
    "summary": "",
    "sentiment": "중립",
    "reliability": "뉴스없음",
    "freshness": "미확인",
    "directness": "미확인",
    "tags": [],
    "risk_flags": [],
    "evidence": [],
    "source_count": 0,
    "relevant_count": 0
   },
   "visible_experimental": true,
   "reaccum": {
    "peak_date": "20260706",
    "peak_value_eok": 642,
    "peak_high_pct": 25.26,
    "peak_turnover_pct": 137.2,
    "peak_ibs": 0.71,
    "peak_uppertail": 12.2,
    "ma20": 7235.5,
    "ma20_margin_pct": 1.17,
    "cause_summary": "과열 경고에도 '호남 반도체' 테마주 상한가 행렬…변동성 주의보[핫...",
    "was_theme_leader": false,
    "source": "live"
   },
   "leader_cohort_prob": null,
   "alert_now": "경고",
   "alert_release": null,
   "alert_release_rule": {
    "source": "KRX_KOSCOM",
    "retrieved_via": "NAVER_FINANCE_NOTICE",
    "notice_date": "20260713",
    "source_url": "https://finance.naver.com/item/news_notice_read.naver?no=66111466&code=091590&page_notice=1",
    "logic_version": "krx-release-v2",
    "parse_status": "unavailable",
    "parse_error": "notice_released"
   },
   "alert_release_checks": null,
   "alert_release_error": "rule_unavailable",
   "alert_elapsed_days": null,
   "alert_risk_released": false,
   "rank_bucket": 2,
   "rank_reason": "저점매집+폭발회전 137% → bucket 2",
   "shadow_bucket": [
    "S2"
   ],
   "expected_touch7_rate": 86.7,
   "expected_high_pct": 17.0,
   "rank_bucket_stats_snapshot": {
    "label": "저점매집+회전90",
    "n": 15,
    "unique_n": 13,
    "touch7_rate": 86.7,
    "expected_high_pct": 17.0,
    "avg_return": 9.09,
    "bucket": 2,
    "basis": "정렬4.md 2026-07-10 확정 스냅샷",
    "population": "overlapping_retro_reference"
   },
   "rank_prior": {
    "source": "chairman_40y_rule",
    "strength": "strong",
    "summary": "저점매집과 폭발일 회전율 90% 이상"
   },
   "rank_policy_name": "rank4",
   "rank_model_version": "rank4-v1",
   "rank_model_source_commit": "7f3acab",
   "rank_model_effective_from": "20260713",
   "rank_model_effective_at": "2026-07-13 09:00:00 KST",
   "precut_rank": 3,
   "published": true,
   "published_rank": 3,
   "theme_leader": false,
   "rank_retro_stats": {
    "basis": "retro",
    "population": "all",
    "model_version": "rank4-v1",
    "n": 14,
    "unique_n": 12,
    "touch7_rate": 85.7,
    "wilson7_lower": 60.1,
    "avg_high_pct": 16.07,
    "median_high_pct": 14.75,
    "min_high_pct": 1.02,
    "valid": true
   },
   "rank_forward_stats": {
    "basis": "forward_saved_signal",
    "population": "eod",
    "model_version": "rank4-v1",
    "n": 0,
    "unique_n": 0,
    "touch7_rate": null,
    "wilson7_lower": null,
    "avg_high_pct": null,
    "median_high_pct": null,
    "min_high_pct": null,
    "valid": false
   }
  },
  {
   "code": "228340",
   "name": "동양파일",
   "sector": "동양파일",
   "pattern": "reaccum",
   "geupso": false,
   "geupso_bars": [],
   "shake": null,
   "deep_shake": null,
   "suspicion_score": 62,
   "calibrated_prob": null,
   "score_breakdown": {
    "base": 62,
    "re_count": 0,
    "re_body": 0,
    "peak_turnover": 0,
    "re_turnover": 0
   },
   "score_raw": 0,
   "score_breakdown_raw": {
    "base": 0,
    "re_count": 0,
    "re_body": 0,
    "peak_turnover": 0,
    "re_turnover": 0
   },
   "forecast": {
    "horizon": "3일 내 +7%",
    "prob_pct": 46,
    "base_pct": 46,
    "strong": false,
    "next_day_7_pct": 25,
    "note": "과거 실측 확률·보장 아님"
   },
   "price": 3350.0,
   "change_pct": -16.15,
   "change_basis": "KRX",
   "high_pct": -3.0,
   "value_eok": 40,
   "snapshot_open": 3870.0,
   "snapshot_high": 3875.0,
   "snapshot_low": 3250.0,
   "snapshot_close": 3350.0,
   "snapshot_volume": 1120307.0,
   "snapshot_value": 4011000000.0,
   "snapshot_value_eok": 40.1,
   "snapshot_as_of": "20260713",
   "signal_date": "20260713",
   "signal_open": 3870.0,
   "signal_high": 3875.0,
   "signal_low": 3250.0,
   "signal_close": 3350.0,
   "signal_prev_close": 3995.0,
   "signal_volume": 1120307.0,
   "signal_value": 4011000000.0,
   "signal_value_eok": 40.1,
   "signal_source": "daily_latest",
   "turnover_pct": 14.0,
   "peak_turnover_pct": null,
   "float_ratio": 0.4,
   "turnover_basis": "float",
   "ma10": 4103.5,
   "ma10_margin_pct": -18.36,
   "spark": {
    "clusters": []
   },
   "spark_max_x": null,
   "spark_max_pct": null,
   "mega_flow": false,
   "reignition": {
    "body_pct": 1.79,
    "time": "14:55",
    "value_eok": 0,
    "count": 1
   },
   "reignition_bars": [
    {
     "time": "14:55",
     "body_pct": 1.79,
     "value_eok": 0
    }
   ],
   "low_accum": true,
   "low_accum_bars": [
    {
     "time": "13:25",
     "body_pct": 2.46
    },
    {
     "time": "14:10",
     "body_pct": 2.52
    },
    {
     "time": "14:15",
     "body_pct": 2.18
    }
   ],
   "news": [],
   "matched_events": [],
   "theme": "반도체",
   "material": {
    "grade": "N",
    "score": 0,
    "summary": "",
    "sentiment": "중립",
    "reliability": "뉴스없음",
    "freshness": "미확인",
    "directness": "미확인",
    "tags": [],
    "risk_flags": [],
    "evidence": [],
    "source_count": 0,
    "relevant_count": 0
   },
   "visible_experimental": true,
   "reaccum": {
    "peak_date": "20260706",
    "peak_value_eok": 0,
    "peak_high_pct": 0.0,
    "peak_turnover_pct": null,
    "peak_ibs": 0.81,
    "peak_uppertail": 3.9,
    "ma20": 3161.6,
    "ma20_margin_pct": 5.96,
    "cause_summary": "",
    "was_theme_leader": false,
    "source": "live"
   },
   "leader_cohort_prob": null,
   "alert_now": "경고",
   "alert_release": false,
   "alert_release_rule": {
    "source": "KRX_KOSCOM",
    "retrieved_via": "NAVER_FINANCE_NOTICE",
    "notice_date": "20260630",
    "designation_date": "20260701",
    "first_review_date_notice": "20260714",
    "first_review_date_adjusted": null,
    "threshold_5d_pct": 45.0,
    "threshold_15d_pct": 75.0,
    "recent_high_window": 15,
    "min_elapsed_days": 10,
    "logic_version": "krx-release-v2",
    "parse_status": "ok",
    "source_url": "https://finance.naver.com/item/news_notice_read.naver?no=49904838&code=228340&page_notice=1",
    "raw_text_hash": "553f6936b147c6e09b42",
    "fetched_at": "2026-07-13 20:43:38 KST",
    "notice_no": "49904838"
   },
   "alert_release_checks": {
    "as_of_date": "20260713",
    "elapsed_days": 9,
    "elapsed_ok": false,
    "five_day_ok": null,
    "fifteen_day_ok": null,
    "not_recent_high_ok": null,
    "halt_days_excluded": []
   },
   "alert_release_error": null,
   "alert_elapsed_days": 9,
   "alert_risk_released": false,
   "rank_bucket": 3,
   "rank_reason": "저점매집+폭발회전 결측 → bucket 3",
   "shadow_bucket": [],
   "expected_touch7_rate": 81.0,
   "expected_high_pct": 15.64,
   "rank_bucket_stats_snapshot": {
    "label": "저점매집 기타",
    "n": 21,
    "unique_n": 17,
    "touch7_rate": 81.0,
    "expected_high_pct": 15.64,
    "avg_return": 6.94,
    "bucket": 3,
    "basis": "정렬4.md 2026-07-10 확정 스냅샷",
    "population": "overlapping_retro_reference"
   },
   "rank_prior": {
    "source": "chairman_40y_rule",
    "strength": "strong",
    "summary": "저점매집 지문"
   },
   "rank_policy_name": "rank4",
   "rank_model_version": "rank4-v1",
   "rank_model_source_commit": "7f3acab",
   "rank_model_effective_from": "20260713",
   "rank_model_effective_at": "2026-07-13 09:00:00 KST",
   "precut_rank": 4,
   "published": true,
   "published_rank": 4,
   "theme_leader": false,
   "rank_retro_stats": {
    "basis": "retro",
    "population": "all",
    "model_version": "rank4-v1",
    "n": 6,
    "unique_n": 5,
    "touch7_rate": 66.7,
    "wilson7_lower": 30.0,
    "avg_high_pct": 12.25,
    "median_high_pct": 13.82,
    "min_high_pct": 0.0,
    "valid": false
   },
   "rank_forward_stats": {
    "basis": "forward_saved_signal",
    "population": "eod",
    "model_version": "rank4-v1",
    "n": 0,
    "unique_n": 0,
    "touch7_rate": null,
    "wilson7_lower": null,
    "avg_high_pct": null,
    "median_high_pct": null,
    "min_high_pct": null,
    "valid": false
   }
  },
  {
   "code": "005360",
   "name": "모나미",
   "sector": "모나미",
   "pattern": "shakeout",
   "shakeout": true,
   "tp_hint": "+13%",
   "fade_pct": 34.5,
   "suspicion_score": 85,
   "score_raw": 0,
   "score_breakdown": {},
   "score_breakdown_raw": {},
   "calibrated_prob": null,
   "forecast": null,
   "shake": null,
   "deep_shake": null,
   "price": 2040.0,
   "change_pct": -4.9,
   "change_basis": "KRX",
   "high_pct": 29.6,
   "value_eok": 418,
   "snapshot_open": 2430.0,
   "snapshot_high": 2780.0,
   "snapshot_low": 2040.0,
   "snapshot_close": 2040.0,
   "snapshot_volume": 16701695.0,
   "snapshot_value": 41817000000.0,
   "snapshot_value_eok": 418.2,
   "snapshot_as_of": "20260713",
   "signal_date": "20260713",
   "signal_open": 2430.0,
   "signal_high": 2780.0,
   "signal_low": 2040.0,
   "signal_close": 2040.0,
   "signal_prev_close": 2145.0,
   "signal_volume": 16701695.0,
   "signal_value": 41817000000.0,
   "signal_value_eok": 418.2,
   "signal_peak6_price": 2780.0,
   "signal_peak60_price": 2780.0,
   "signal_ma20": 1374.7,
   "signal_ma10": 1495.1,
   "signal_source": "daily_latest",
   "turnover_pct": 124.5,
   "float_ratio": 0.7098,
   "turnover_basis": "float",
   "turnover_2d_pct": 187.3,
   "turnover_band": 2,
   "peak_dd_pct": -26.6,
   "dd_band": 1,
   "dd6_pct": -26.6,
   "very_good": false,
   "very_good_tier": "candidate",
   "very_good_candidate": true,
   "strength_tier": 3,
   "strength": "조합D(통계상 고가강)",
   "run_6d_pct": 54.1,
   "ma20_gap_pct": 48.4,
   "ma10": 1495.1,
   "ma10_margin_pct": 36.45,
   "spark": {
    "clusters": []
   },
   "spark_max_x": null,
   "spark_max_pct": null,
   "mega_flow": false,
   "reignition": null,
   "reignition_bars": [],
   "geupso": false,
   "geupso_bars": [],
   "low_accum": false,
   "low_accum_bars": [],
   "news": [
    {
     "title": "이대로 못 무너진다…'상폐 위기' 토종 中企 살리기 눈길",
     "summary": "정부의 상장폐지 요건 강화로 벼랑 끝에 몰린 토종 중소기업을 살리기 위한 주주와 기업 움직임이 본격화하고 있다. 국민 문구 업체인 모나미에 소액주주들의 매수세가 쏠리며 주가가 급등한 가운데, 민생과 사회에 기여해온 다른 기업들 역시...",
     "office": "이데일리",
     "datetime": "202607131626",
     "url": "https://n.news.naver.com/mnews/article/018/0006329280",
     "sentiment": "혼재"
    },
    {
     "title": "모나미·한성기업 상폐 기준 넘겼다…‘응원 매수’가 밀어올린 시총...",
     "summary": "참전용사 후원·국산 볼펜 상징성이 매수 촉발 모나미 405억원·한성기업 525억원으로 회복 내년 1월 기준선 500억원, 실적 개선이 관건 [헤럴드경제=홍석희 기자] 코스피 상장사 모나미와 한성기업이 상장폐지 위기에서 벗어났다. 과거...",
     "office": "헤럴드경제",
     "datetime": "202607131600",
     "url": "https://n.news.naver.com/mnews/article/016/0002669613",
     "sentiment": "혼재"
    },
    {
     "title": "한성기업 이어 모나미도 ‘애국주’ 붐 탑승…장중 20%대 급등",
     "summary": "시총 470억 돌파로 상폐 면혀 “K증시의 신종 주주 행동주의” 모나미 대표 자필 감사문 업로드 문구 기업 모나미 주가가 독도 관련 기부와 독립유공자 후원 활동 등이 재조명되며 3거래일째 20%대 상승세를 보이고 있다. 최근 시가총액 요건 강화로...",
     "office": "매경이코노미",
     "datetime": "202607131538",
     "url": "https://n.news.naver.com/mnews/article/024/0000106840",
     "sentiment": "호재"
    },
    {
     "title": "&quot;여러분이 지켜줘 감사&quot;…상장폐지 위기 넘긴 모나미 사장 자필 편지",
     "summary": "상장폐지 위기에 몰린 문구기업 모나미에 대한 '응원 투자'가 이어지자 모나미 사장이 자사 홈페이지에 자필 감사문을 올렸다. 시가총액이 상장유지 기준을 넘어서자 감사의 마음을 전한 것이다. 13일 모나미 홈페이지에는 송재화 사장의 자필...",
     "office": "TV조선",
     "datetime": "202607131431",
     "url": "https://n.news.naver.com/mnews/article/448/0000626386",
     "sentiment": "혼재"
    },
    {
     "title": "&quot;착한 기업, 돈쭐 내서 상폐막자&quot;…한성기업·모나미 신고가",
     "summary": "한성기업과 모나미가 국내 투자자들의 '착한 기업 살리기 운동'에 힘입어 상승 중이다. 한성기업은 52주 신고가를 경신했다. 13일 오전 9시17분 현재 한성기업은 전 거래일 대비 1710원(20.21%) 오른 1만170원에 거래 중이다. 장 중 1만9",
     "office": "머니투데이",
     "datetime": "202607130923",
     "url": "https://n.news.naver.com/mnews/article/008/0005384939",
     "sentiment": "호재"
    },
    {
     "title": "“오늘도 돈쭐 내주자” 애국 개미 우르르…3연상 질주",
     "summary": "상장폐지 위기에 처한 ‘애국 기업’에 대한 투자 열풍이 불면서 주가가 급등하는 사례가 이어지고 있다. 김인겸 한성기업 마케팅실장(사진=이데일리 김미경 기자) 13일 엠피닥터에 따르면 이날 오전 9시 8분 기준 모나미(005360)는 전장 대비...",
     "office": "이데일리",
     "datetime": "202607130921",
     "url": "https://n.news.naver.com/mnews/article/018/0006328906",
     "sentiment": "혼재"
    }
   ],
   "matched_events": [],
   "theme": "",
   "material": {
    "grade": "C",
    "score": 45,
    "summary": "&quot;착한 기업, 돈쭐 내서 상폐막자&quot;…한성기업·모나미 신고가",
    "sentiment": "호재",
    "reliability": "뉴스",
    "freshness": "당일~1일",
    "freshness_days": 0.18,
    "directness": "직접",
    "tags": [
     "S급재료",
     "공시/대형이벤트",
     "모나미",
     "실적/재무",
     "테마/수혜"
    ],
    "risk_flags": [
     "상장폐지",
     "상폐"
    ],
    "evidence": [
     {
      "title": "&quot;착한 기업, 돈쭐 내서 상폐막자&quot;…한성기업·모나미 신고가",
      "datetime": "202607130923",
      "source": "머니투데이",
      "url": "https://n.news.naver.com/mnews/article/008/0005384939",
      "score": 100
     },
     {
      "title": "&quot;여러분이 지켜줘 감사&quot;…상장폐지 위기 넘긴 모나미 사장 자필 편지",
      "datetime": "202607131431",
      "source": "TV조선",
      "url": "https://n.news.naver.com/mnews/article/448/0000626386",
      "score": 100
     },
     {
      "title": "“오늘도 돈쭐 내주자” 애국 개미 우르르…3연상 질주",
      "datetime": "202607130921",
      "source": "이데일리",
      "url": "https://n.news.naver.com/mnews/article/018/0006328906",
      "score": 100
     },
     {
      "title": "한성기업 이어 모나미도 ‘애국주’ 붐 탑승…장중 20%대 급등",
      "datetime": "202607131538",
      "source": "매경이코노미",
      "url": "https://n.news.naver.com/mnews/article/024/0000106840",
      "score": 94
     },
     {
      "title": "모나미·한성기업 상폐 기준 넘겼다…‘응원 매수’가 밀어올린 시총...",
      "datetime": "202607131600",
      "source": "헤럴드경제",
      "url": "https://n.news.naver.com/mnews/article/016/0002669613",
      "score": 90
     }
    ],
    "source_count": 6,
    "relevant_count": 6
   },
   "visible_experimental": true,
   "alert_now": "주의",
   "rank_bucket": 4,
   "rank_reason": "흔들기+조합D+85점 → bucket 4",
   "shadow_bucket": [
    "S4"
   ],
   "expected_touch7_rate": 88.9,
   "expected_high_pct": 17.75,
   "rank_bucket_stats_snapshot": {
    "label": "흔들기+조합D+75점",
    "n": 9,
    "unique_n": 8,
    "touch7_rate": 88.9,
    "expected_high_pct": 17.75,
    "avg_return": 3.3,
    "bucket": 4,
    "basis": "정렬4.md 2026-07-10 확정 스냅샷",
    "population": "overlapping_retro_reference"
   },
   "rank_prior": {
    "source": "agreed_rule",
    "strength": "strong",
    "summary": "흔들기·조합D·75점 이상"
   },
   "rank_policy_name": "rank4",
   "rank_model_version": "rank4-v1",
   "rank_model_source_commit": "7f3acab",
   "rank_model_effective_from": "20260713",
   "rank_model_effective_at": "2026-07-13 09:00:00 KST",
   "precut_rank": 5,
   "published": true,
   "published_rank": 5,
   "theme_leader": false,
   "rank_retro_stats": {
    "basis": "retro",
    "population": "all",
    "model_version": "rank4-v1",
    "n": 9,
    "unique_n": 8,
    "touch7_rate": 88.9,
    "wilson7_lower": 56.5,
    "avg_high_pct": 16.45,
    "median_high_pct": 16.64,
    "min_high_pct": 3.43,
    "valid": false
   },
   "rank_forward_stats": {
    "basis": "forward_saved_signal",
    "population": "eod",
    "model_version": "rank4-v1",
    "n": 0,
    "unique_n": 0,
    "touch7_rate": null,
    "wilson7_lower": null,
    "avg_high_pct": null,
    "median_high_pct": null,
    "min_high_pct": null,
    "valid": false
   }
  },
  {
   "code": "003680",
   "name": "한성기업",
   "sector": "한성기업",
   "pattern": "shakeout",
   "shakeout": true,
   "tp_hint": "+13%",
   "fade_pct": 20.0,
   "suspicion_score": 82,
   "score_raw": 0,
   "score_breakdown": {},
   "score_breakdown_raw": {},
   "calibrated_prob": null,
   "forecast": null,
   "shake": null,
   "deep_shake": null,
   "price": 9300.0,
   "change_pct": 9.93,
   "change_basis": "KRX",
   "high_pct": 29.91,
   "value_eok": 1121,
   "snapshot_open": 10230.0,
   "snapshot_high": 10990.0,
   "snapshot_low": 8860.0,
   "snapshot_close": 9300.0,
   "snapshot_volume": 10950600.0,
   "snapshot_value": 112142000000.0,
   "snapshot_value_eok": 1121.4,
   "snapshot_as_of": "20260713",
   "signal_date": "20260713",
   "signal_open": 10230.0,
   "signal_high": 10990.0,
   "signal_low": 8860.0,
   "signal_close": 9300.0,
   "signal_prev_close": 8460.0,
   "signal_volume": 10950600.0,
   "signal_value": 112142000000.0,
   "signal_value_eok": 1121.4,
   "signal_peak6_price": 10990.0,
   "signal_peak60_price": 10990.0,
   "signal_ma20": 4967.2,
   "signal_ma10": 5574.5,
   "signal_source": "daily_latest",
   "turnover_pct": 340.4,
   "float_ratio": 0.5181,
   "turnover_basis": "float",
   "turnover_2d_pct": 387.9,
   "turnover_band": 2,
   "peak_dd_pct": -15.4,
   "dd_band": 2,
   "dd6_pct": -15.4,
   "very_good": false,
   "very_good_tier": null,
   "very_good_candidate": false,
   "strength_tier": 4,
   "strength": "조합D(통계상 고가강)",
   "run_6d_pct": 119.9,
   "ma20_gap_pct": 87.2,
   "ma10": 5574.5,
   "ma10_margin_pct": 66.83,
   "spark": {
    "clusters": []
   },
   "spark_max_x": null,
   "spark_max_pct": null,
   "mega_flow": false,
   "reignition": null,
   "reignition_bars": [],
   "geupso": false,
   "geupso_bars": [],
   "low_accum": false,
   "low_accum_bars": [],
   "news": [
    {
     "title": "모나미·한성기업 상폐 기준 넘겼다…‘응원 매수’가 밀어올린 시총...",
     "summary": "참전용사 후원·국산 볼펜 상징성이 매수 촉발 모나미 405억원·한성기업 525억원으로 회복 내년 1월 기준선 500억원, 실적 개선이 관건 [헤럴드경제=홍석희 기자] 코스피 상장사 모나미와 한성기업이 상장폐지 위기에서 벗어났다. 과거...",
     "office": "헤럴드경제",
     "datetime": "202607131600",
     "url": "https://n.news.naver.com/mnews/article/016/0002669613",
     "sentiment": "혼재"
    },
    {
     "title": "한성기업 이어 모나미도 ‘애국주’ 붐 탑승…장중 20%대 급등",
     "summary": "시총 470억 돌파로 상폐 면혀 “K증시의 신종 주주 행동주의” 모나미 대표 자필 감사문 업로드 문구 기업 모나미 주가가 독도 관련 기부와 독립유공자 후원 활동 등이 재조명되며 3거래일째 20%대 상승세를 보이고 있다. 최근 시가총액 요건 강화로...",
     "office": "매경이코노미",
     "datetime": "202607131538",
     "url": "https://n.news.naver.com/mnews/article/024/0000106840",
     "sentiment": "호재"
    },
    {
     "title": "&quot;착한 기업, 돈쭐 내서 상폐막자&quot;…한성기업·모나미 신고가",
     "summary": "한성기업과 모나미가 국내 투자자들의 '착한 기업 살리기 운동'에 힘입어 상승 중이다. 한성기업은 52주 신고가를 경신했다. 13일 오전 9시17분 현재 한성기업은 전 거래일 대비 1710원(20.21%) 오른 1만170원에 거래 중이다. 장 중 1만9",
     "office": "머니투데이",
     "datetime": "202607130923",
     "url": "https://n.news.naver.com/mnews/article/008/0005384939",
     "sentiment": "호재"
    },
    {
     "title": "“오늘도 돈쭐 내주자” 애국 개미 우르르…3연상 질주",
     "summary": "상장폐지 위기에 처한 ‘애국 기업’에 대한 투자 열풍이 불면서 주가가 급등하는 사례가 이어지고 있다. 김인겸 한성기업 마케팅실장(사진=이데일리 김미경 기자) 13일 엠피닥터에 따르면 이날 오전 9시 8분 기준 모나미(005360)는 전장 대비...",
     "office": "이데일리",
     "datetime": "202607130921",
     "url": "https://n.news.naver.com/mnews/article/018/0006328906",
     "sentiment": "혼재"
    },
    {
     "title": "하락장 비켜간 ‘미담·지역 테마주’…한성기업 일주일 새 2배↑[이런...",
     "summary": "국내 증시가 약세를 보인 지난주 기업 실적이나 수주보다 ‘온라인상 미담’과 ‘지역 개발 기대’를 앞세운 테마주가 급등했다. 일부 종목은 일주일 만에 주가가 두 배로 뛰었고 한국거래소가 시장경보를 발동한 뒤에도 상승세를 이어갔다. 13일...",
     "office": "서울경제",
     "datetime": "202607130712",
     "url": "https://n.news.naver.com/mnews/article/011/0004640826",
     "sentiment": "혼재"
    }
   ],
   "matched_events": [],
   "theme": "",
   "material": {
    "grade": "C",
    "score": 45,
    "summary": "&quot;착한 기업, 돈쭐 내서 상폐막자&quot;…한성기업·모나미 신고가",
    "sentiment": "호재",
    "reliability": "공시+뉴스",
    "freshness": "당일~1일",
    "freshness_days": 0.2,
    "directness": "직접",
    "tags": [
     "S급재료",
     "공시",
     "공시/대형이벤트",
     "실적/재무",
     "테마/수혜",
     "한성기업"
    ],
    "risk_flags": [
     "상장폐지",
     "상폐"
    ],
    "evidence": [
     {
      "title": "&quot;착한 기업, 돈쭐 내서 상폐막자&quot;…한성기업·모나미 신고가",
      "datetime": "202607130923",
      "source": "머니투데이",
      "url": "https://n.news.naver.com/mnews/article/008/0005384939",
      "score": 100
     },
     {
      "title": "“오늘도 돈쭐 내주자” 애국 개미 우르르…3연상 질주",
      "datetime": "202607130921",
      "source": "이데일리",
      "url": "https://n.news.naver.com/mnews/article/018/0006328906",
      "score": 100
     },
     {
      "title": "한성기업 이어 모나미도 ‘애국주’ 붐 탑승…장중 20%대 급등",
      "datetime": "202607131538",
      "source": "매경이코노미",
      "url": "https://n.news.naver.com/mnews/article/024/0000106840",
      "score": 94
     },
     {
      "title": "하락장 비켜간 ‘미담·지역 테마주’…한성기업 일주일 새 2배↑[이런...",
      "datetime": "202607130712",
      "source": "서울경제",
      "url": "https://n.news.naver.com/mnews/article/011/0004640826",
      "score": 93
     },
     {
      "title": "모나미·한성기업 상폐 기준 넘겼다…‘응원 매수’가 밀어올린 시총...",
      "datetime": "202607131600",
      "source": "헤럴드경제",
      "url": "https://n.news.naver.com/mnews/article/016/0002669613",
      "score": 90
     }
    ],
    "source_count": 5,
    "relevant_count": 5
   },
   "visible_experimental": true,
   "alert_now": "주의",
   "rank_bucket": 4,
   "rank_reason": "흔들기+조합D+82점 → bucket 4",
   "shadow_bucket": [
    "S4"
   ],
   "expected_touch7_rate": 88.9,
   "expected_high_pct": 17.75,
   "rank_bucket_stats_snapshot": {
    "label": "흔들기+조합D+75점",
    "n": 9,
    "unique_n": 8,
    "touch7_rate": 88.9,
    "expected_high_pct": 17.75,
    "avg_return": 3.3,
    "bucket": 4,
    "basis": "정렬4.md 2026-07-10 확정 스냅샷",
    "population": "overlapping_retro_reference"
   },
   "rank_prior": {
    "source": "agreed_rule",
    "strength": "strong",
    "summary": "흔들기·조합D·75점 이상"
   },
   "rank_policy_name": "rank4",
   "rank_model_version": "rank4-v1",
   "rank_model_source_commit": "7f3acab",
   "rank_model_effective_from": "20260713",
   "rank_model_effective_at": "2026-07-13 09:00:00 KST",
   "precut_rank": 6,
   "published": true,
   "published_rank": 6,
   "theme_leader": false,
   "rank_retro_stats": {
    "basis": "retro",
    "population": "all",
    "model_version": "rank4-v1",
    "n": 9,
    "unique_n": 8,
    "touch7_rate": 88.9,
    "wilson7_lower": 56.5,
    "avg_high_pct": 16.45,
    "median_high_pct": 16.64,
    "min_high_pct": 3.43,
    "valid": false
   },
   "rank_forward_stats": {
    "basis": "forward_saved_signal",
    "population": "eod",
    "model_version": "rank4-v1",
    "n": 0,
    "unique_n": 0,
    "touch7_rate": null,
    "wilson7_lower": null,
    "avg_high_pct": null,
    "median_high_pct": null,
    "min_high_pct": null,
    "valid": false
   }
  },
  {
   "code": "006660",
   "name": "삼성공조",
   "sector": "삼성공조",
   "pattern": "shakeout",
   "shakeout": true,
   "tp_hint": "+7~10% (12% 천장 실측)",
   "fade_pct": 19.0,
   "suspicion_score": 74,
   "score_raw": 0,
   "score_breakdown": {},
   "score_breakdown_raw": {},
   "calibrated_prob": null,
   "forecast": null,
   "shake": null,
   "deep_shake": null,
   "price": 10080.0,
   "change_pct": 5.88,
   "change_basis": "KRX",
   "high_pct": 24.89,
   "value_eok": 433,
   "snapshot_open": 9570.0,
   "snapshot_high": 11890.0,
   "snapshot_low": 9540.0,
   "snapshot_close": 10080.0,
   "snapshot_volume": 3925280.0,
   "snapshot_value": 43323000000.0,
   "snapshot_value_eok": 433.2,
   "snapshot_as_of": "20260713",
   "signal_date": "20260713",
   "signal_open": 9570.0,
   "signal_high": 11890.0,
   "signal_low": 9540.0,
   "signal_close": 10080.0,
   "signal_prev_close": 9520.0,
   "signal_volume": 3925280.0,
   "signal_value": 43323000000.0,
   "signal_value_eok": 433.2,
   "signal_peak6_price": 11890.0,
   "signal_peak60_price": 20000.0,
   "signal_ma20": 10015.5,
   "signal_ma10": 9626.0,
   "signal_source": "daily_latest",
   "turnover_pct": 101.6,
   "float_ratio": 0.4754,
   "turnover_basis": "float",
   "turnover_2d_pct": 104.3,
   "turnover_band": 0,
   "peak_dd_pct": -49.6,
   "dd_band": 1,
   "dd6_pct": -15.2,
   "very_good": false,
   "very_good_tier": null,
   "very_good_candidate": false,
   "strength_tier": 1,
   "strength": "조합B(인접·검증중)",
   "run_6d_pct": 7.0,
   "ma20_gap_pct": 0.6,
   "ma10": 9626.0,
   "ma10_margin_pct": 4.72,
   "spark": {
    "clusters": []
   },
   "spark_max_x": null,
   "spark_max_pct": null,
   "mega_flow": false,
   "reignition": null,
   "reignition_bars": [],
   "geupso": false,
   "geupso_bars": [],
   "low_accum": false,
   "low_accum_bars": [],
   "news": [
    {
     "title": "홍대 고깃집 간다니 삼겹살주 급등…‘무지성’ 젠슨 황 테마주의 촌...",
     "summary": "소맥 회동에 돼지고기·소주·소금 관련주까지 거론 깐부치킨·삼성공조 이어 또 등장한 ‘황당 테마주’ ““황형의 삼겹살 관련주, 다 풀어드립니다.” ” 젠슨 황 엔비디아 최고경영자(CEO)의 방한 당일인 오늘(5일) 오전, 국내 한 주식 커뮤니티에...",
     "office": "조선비즈",
     "datetime": "202606051534",
     "url": "https://n.news.naver.com/mnews/article/366/0001169708",
     "sentiment": "호재"
    },
    {
     "title": "삼성공조, 지난해 영업익 32억…전년비 49.9% ↓",
     "summary": "삼성공조는 지난해 연결기준 영업이익이 32억4510만원으로 전년대비 49.9% 감소했다고 24일 공시했다. 같은 기간 매출액은 1177억3635만원으로 1.7% 증가한 것으로 나타났다. 당기순이익은 72억3955만원으로 51.4% 줄어든 것으로 집계됐",
     "office": "헤럴드경제",
     "datetime": "202602241651",
     "url": "https://n.news.naver.com/mnews/article/016/0002604432",
     "sentiment": "혼재"
    }
   ],
   "matched_events": [],
   "theme": "수급",
   "material": {
    "grade": "A",
    "score": 84,
    "summary": "삼성공조, 지난해 영업익 32억…전년비 49.9% ↓",
    "sentiment": "호재",
    "reliability": "공시+뉴스",
    "freshness": "오래됨",
    "freshness_days": 38.21,
    "directness": "직접",
    "tags": [
     "공시",
     "공시/대형이벤트",
     "수급",
     "실적/재무",
     "테마/수혜"
    ],
    "risk_flags": [],
    "evidence": [
     {
      "title": "삼성공조, 지난해 영업익 32억…전년비 49.9% ↓",
      "datetime": "202602241651",
      "source": "헤럴드경제",
      "url": "https://n.news.naver.com/mnews/article/016/0002604432",
      "score": 82
     },
     {
      "title": "홍대 고깃집 간다니 삼겹살주 급등…‘무지성’ 젠슨 황 테마주의 촌...",
      "datetime": "202606051534",
      "source": "조선비즈",
      "url": "https://n.news.naver.com/mnews/article/366/0001169708",
      "score": 29
     }
    ],
    "source_count": 2,
    "relevant_count": 2
   },
   "visible_experimental": true,
   "alert_now": null,
   "rank_bucket": 8,
   "rank_reason": "흔들기 기타 → bucket 8",
   "shadow_bucket": [],
   "expected_touch7_rate": 76.9,
   "expected_high_pct": 14.59,
   "rank_bucket_stats_snapshot": {
    "label": "흔들기 기타",
    "n": 26,
    "unique_n": 21,
    "touch7_rate": 76.9,
    "expected_high_pct": 14.59,
    "avg_return": 1.69,
    "bucket": 8,
    "basis": "정렬4.md 2026-07-10 확정 스냅샷",
    "population": "overlapping_retro_reference"
   },
   "rank_prior": {
    "source": "agreed_rule",
    "strength": "medium",
    "summary": "흔들기 기타"
   },
   "rank_policy_name": "rank4",
   "rank_model_version": "rank4-v1",
   "rank_model_source_commit": "7f3acab",
   "rank_model_effective_from": "20260713",
   "rank_model_effective_at": "2026-07-13 09:00:00 KST",
   "precut_rank": 7,
   "published": true,
   "published_rank": 7,
   "theme_leader": false,
   "rank_retro_stats": {
    "basis": "retro",
    "population": "all",
    "model_version": "rank4-v1",
    "n": 8,
    "unique_n": 8,
    "touch7_rate": 75.0,
    "wilson7_lower": 40.9,
    "avg_high_pct": 11.04,
    "median_high_pct": 10.1,
    "min_high_pct": 0.37,
    "valid": false
   },
   "rank_forward_stats": {
    "basis": "forward_saved_signal",
    "population": "eod",
    "model_version": "rank4-v1",
    "n": 0,
    "unique_n": 0,
    "touch7_rate": null,
    "wilson7_lower": null,
    "avg_high_pct": null,
    "median_high_pct": null,
    "min_high_pct": null,
    "valid": false
   }
  },
  {
   "code": "002700",
   "name": "신일전자",
   "sector": "신일전자",
   "pattern": "shakeout",
   "shakeout": true,
   "tp_hint": "70~90% 관찰 밴드(표본소)",
   "fade_pct": 17.0,
   "suspicion_score": 71,
   "score_raw": 0,
   "score_breakdown": {},
   "score_breakdown_raw": {},
   "calibrated_prob": null,
   "forecast": null,
   "shake": null,
   "deep_shake": null,
   "price": 1195.0,
   "change_pct": 9.83,
   "change_basis": "KRX",
   "high_pct": 26.84,
   "value_eok": 564,
   "snapshot_open": 1136.0,
   "snapshot_high": 1380.0,
   "snapshot_low": 1136.0,
   "snapshot_close": 1195.0,
   "snapshot_volume": 43799765.0,
   "snapshot_value": 56445000000.0,
   "snapshot_value_eok": 564.5,
   "snapshot_as_of": "20260713",
   "signal_date": "20260713",
   "signal_open": 1136.0,
   "signal_high": 1380.0,
   "signal_low": 1136.0,
   "signal_close": 1195.0,
   "signal_prev_close": 1088.0,
   "signal_volume": 43799765.0,
   "signal_value": 56445000000.0,
   "signal_value_eok": 564.5,
   "signal_peak6_price": 1430.0,
   "signal_peak60_price": 1501.0,
   "signal_ma20": 1141.5,
   "signal_ma10": 1142.8,
   "signal_source": "daily_latest",
   "turnover_pct": 80.7,
   "float_ratio": 0.7917000000000001,
   "turnover_basis": "float",
   "turnover_2d_pct": 82.5,
   "turnover_band": 1,
   "peak_dd_pct": -20.4,
   "dd_band": 1,
   "dd6_pct": -16.4,
   "very_good": false,
   "very_good_tier": null,
   "very_good_candidate": false,
   "strength_tier": 2,
   "strength": "조합C(중립)",
   "run_6d_pct": 2.4,
   "ma20_gap_pct": 4.7,
   "ma10": 1142.8,
   "ma10_margin_pct": 4.57,
   "spark": {
    "clusters": []
   },
   "spark_max_x": null,
   "spark_max_pct": null,
   "mega_flow": false,
   "reignition": null,
   "reignition_bars": [],
   "geupso": false,
   "geupso_bars": [],
   "low_accum": false,
   "low_accum_bars": [],
   "news": [
    {
     "title": "신일전자, 최대 28m 바람 전달 '리본 블레이드 팬' 출시",
     "summary": "신일전자가 바람 전달력과 공기 순환 성능을 강화한 BLDC 선풍기 '리본 블레이드 팬'을 출시했다고 9일 밝혔다. 신제품은 공기역학을 반영한 4세대 리본형 날개를 탑재한 것이 특징이다. 곡선형 날개 구조가 공기 흐름을 안정적으로 유지해 바람...",
     "office": "아이뉴스24",
     "datetime": "202607091714",
     "url": "https://n.news.naver.com/mnews/article/031/0001041098",
     "sentiment": "호재"
    }
   ],
   "matched_events": [],
   "theme": "반도체",
   "material": {
    "grade": "C",
    "score": 52,
    "summary": "신일전자, 최대 28m 바람 전달 '리본 블레이드 팬' 출시",
    "sentiment": "호재",
    "reliability": "뉴스",
    "freshness": "1주내",
    "freshness_days": 4.15,
    "directness": "직접",
    "tags": [
     "반도체",
     "실적/재무"
    ],
    "risk_flags": [],
    "evidence": [
     {
      "title": "신일전자, 최대 28m 바람 전달 '리본 블레이드 팬' 출시",
      "datetime": "202607091714",
      "source": "아이뉴스24",
      "url": "https://n.news.naver.com/mnews/article/031/0001041098",
      "score": 52
     }
    ],
    "source_count": 1,
    "relevant_count": 1
   },
   "visible_experimental": true,
   "alert_now": null,
   "rank_bucket": 8,
   "rank_reason": "흔들기 기타 → bucket 8",
   "shadow_bucket": [],
   "expected_touch7_rate": 76.9,
   "expected_high_pct": 14.59,
   "rank_bucket_stats_snapshot": {
    "label": "흔들기 기타",
    "n": 26,
    "unique_n": 21,
    "touch7_rate": 76.9,
    "expected_high_pct": 14.59,
    "avg_return": 1.69,
    "bucket": 8,
    "basis": "정렬4.md 2026-07-10 확정 스냅샷",
    "population": "overlapping_retro_reference"
   },
   "rank_prior": {
    "source": "agreed_rule",
    "strength": "medium",
    "summary": "흔들기 기타"
   },
   "rank_policy_name": "rank4",
   "rank_model_version": "rank4-v1",
   "rank_model_source_commit": "7f3acab",
   "rank_model_effective_from": "20260713",
   "rank_model_effective_at": "2026-07-13 09:00:00 KST",
   "precut_rank": 8,
   "published": true,
   "published_rank": 8,
   "theme_leader": true,
   "rank_retro_stats": {
    "basis": "retro",
    "population": "all",
    "model_version": "rank4-v1",
    "n": 8,
    "unique_n": 8,
    "touch7_rate": 75.0,
    "wilson7_lower": 40.9,
    "avg_high_pct": 11.04,
    "median_high_pct": 10.1,
    "min_high_pct": 0.37,
    "valid": false
   },
   "rank_forward_stats": {
    "basis": "forward_saved_signal",
    "population": "eod",
    "model_version": "rank4-v1",
    "n": 0,
    "unique_n": 0,
    "touch7_rate": null,
    "wilson7_lower": null,
    "avg_high_pct": null,
    "median_high_pct": null,
    "min_high_pct": null,
    "valid": false
   }
  },
  {
   "code": "042110",
   "name": "에스씨디",
   "sector": "에스씨디",
   "pattern": "shakeout",
   "shakeout": true,
   "tp_hint": "70~90% 관찰 밴드(표본소)",
   "fade_pct": 15.8,
   "suspicion_score": 71,
   "score_raw": 0,
   "score_breakdown": {},
   "score_breakdown_raw": {},
   "calibrated_prob": null,
   "forecast": null,
   "shake": null,
   "deep_shake": null,
   "price": 1249.0,
   "change_pct": 13.13,
   "change_basis": "KRX",
   "high_pct": 28.89,
   "value_eok": 254,
   "snapshot_open": 1104.0,
   "snapshot_high": 1423.0,
   "snapshot_low": 1104.0,
   "snapshot_close": 1249.0,
   "snapshot_volume": 19444313.0,
   "snapshot_value": 25351000000.0,
   "snapshot_value_eok": 253.5,
   "snapshot_as_of": "20260713",
   "signal_date": "20260713",
   "signal_open": 1104.0,
   "signal_high": 1423.0,
   "signal_low": 1104.0,
   "signal_close": 1249.0,
   "signal_prev_close": 1104.0,
   "signal_volume": 19444313.0,
   "signal_value": 25351000000.0,
   "signal_value_eok": 253.5,
   "signal_peak6_price": 1423.0,
   "signal_peak60_price": 1672.0,
   "signal_ma20": 1129.6,
   "signal_ma10": 1128.9,
   "signal_source": "daily_latest",
   "turnover_pct": 82.8,
   "float_ratio": 0.4858,
   "turnover_basis": "float",
   "turnover_2d_pct": 83.7,
   "turnover_band": 1,
   "peak_dd_pct": -25.3,
   "dd_band": 1,
   "dd6_pct": -12.2,
   "very_good": false,
   "very_good_tier": null,
   "very_good_candidate": false,
   "strength_tier": 2,
   "strength": "조합C(중립)",
   "run_6d_pct": 7.2,
   "ma20_gap_pct": 10.6,
   "ma10": 1128.9,
   "ma10_margin_pct": 10.64,
   "spark": {
    "clusters": []
   },
   "spark_max_x": null,
   "spark_max_pct": null,
   "mega_flow": false,
   "reignition": null,
   "reignition_bars": [],
   "geupso": false,
   "geupso_bars": [],
   "low_accum": false,
   "low_accum_bars": [],
   "news": [
    {
     "title": "에스씨디, 냉장고·에어컨 부품 2종 개발 양산 들어가",
     "summary": "제어장치·전자부품 기업 에스씨디가 냉장고와 에어컨 제품 경쟁력을 높일 수 있는 신제품 'DC 아이스셔터(DC ICE SHUTTER)'와 'SPOKE BLDC 모터' 등 2종을 개발하고 고객사 대상 마케팅에 나선다고 26일 밝혔다. DC 아이스셔터는 냉",
     "office": "아이뉴스24",
     "datetime": "202603261800",
     "url": "https://n.news.naver.com/mnews/article/031/0001017196",
     "sentiment": "호재"
    },
    {
     "title": "에스씨디 “올해 가전부품 수출처 다변화”",
     "summary": "수익성 개선에도 주력…주당 50원 현금배당 제어장치 전문기업 에스씨디(대표 오길호)가 올해 각종 전자부품의 수출처 다변화에 주력한다. 최근 판매호조를 보이는 냉장고용 오토도어오픈 장치의 판매 확대와 함께 세탁기 등 타 가전제품으로...",
     "office": "헤럴드경제",
     "datetime": "202602271052",
     "url": "https://n.news.naver.com/mnews/article/016/0002606160",
     "sentiment": "호재"
    },
    {
     "title": "SCD 주주연합, 감사 선임 제안",
     "summary": "코스닥 상장법인 에스씨디(SCD)의 소수주주들이 감사 선임을 주주총회 안건으로 제안했다. 25일 금융투자업계에 따르면 에스씨디 개인주주연합은 지난 10일과 20일 두 차례에 걸쳐 3·4차 주주제안서를 발송했다. 제안서에는 주당 50원 배당과 50억원의",
     "office": "아이뉴스24",
     "datetime": "202602251112",
     "url": "https://n.news.naver.com/mnews/article/031/0001008169",
     "sentiment": "호재"
    }
   ],
   "matched_events": [
    {
     "id": "2026-07-14_미국 CPI 발표 (6",
     "title": "미국 CPI 발표 (6월분)",
     "dday": 1,
     "categories": [
      "환율"
     ],
     "score": 2.5
    }
   ],
   "theme": "환율",
   "material": {
    "grade": "B",
    "score": 68,
    "summary": "SCD 주주연합, 감사 선임 제안",
    "sentiment": "호재",
    "reliability": "공시+뉴스",
    "freshness": "오래됨",
    "freshness_days": 109.11,
    "directness": "직접",
    "tags": [
     "공시",
     "공시/대형이벤트",
     "실적/재무",
     "환율"
    ],
    "risk_flags": [],
    "evidence": [
     {
      "title": "SCD 주주연합, 감사 선임 제안",
      "datetime": "202602251112",
      "source": "아이뉴스24",
      "url": "https://n.news.naver.com/mnews/article/031/0001008169",
      "score": 62
     },
     {
      "title": "에스씨디 “올해 가전부품 수출처 다변화”",
      "datetime": "202602271052",
      "source": "헤럴드경제",
      "url": "https://n.news.naver.com/mnews/article/016/0002606160",
      "score": 52
     },
     {
      "title": "에스씨디, 냉장고·에어컨 부품 2종 개발 양산 들어가",
      "datetime": "202603261800",
      "source": "아이뉴스24",
      "url": "https://n.news.naver.com/mnews/article/031/0001017196",
      "score": 44
     }
    ],
    "source_count": 3,
    "relevant_count": 3
   },
   "visible_experimental": true,
   "alert_now": null,
   "rank_bucket": 8,
   "rank_reason": "흔들기 기타 → bucket 8",
   "shadow_bucket": [],
   "expected_touch7_rate": 76.9,
   "expected_high_pct": 14.59,
   "rank_bucket_stats_snapshot": {
    "label": "흔들기 기타",
    "n": 26,
    "unique_n": 21,
    "touch7_rate": 76.9,
    "expected_high_pct": 14.59,
    "avg_return": 1.69,
    "bucket": 8,
    "basis": "정렬4.md 2026-07-10 확정 스냅샷",
    "population": "overlapping_retro_reference"
   },
   "rank_prior": {
    "source": "agreed_rule",
    "strength": "medium",
    "summary": "흔들기 기타"
   },
   "rank_policy_name": "rank4",
   "rank_model_version": "rank4-v1",
   "rank_model_source_commit": "7f3acab",
   "rank_model_effective_from": "20260713",
   "rank_model_effective_at": "2026-07-13 09:00:00 KST",
   "precut_rank": 9,
   "published": true,
   "published_rank": 9,
   "theme_leader": false,
   "rank_retro_stats": {
    "basis": "retro",
    "population": "all",
    "model_version": "rank4-v1",
    "n": 8,
    "unique_n": 8,
    "touch7_rate": 75.0,
    "wilson7_lower": 40.9,
    "avg_high_pct": 11.04,
    "median_high_pct": 10.1,
    "min_high_pct": 0.37,
    "valid": false
   },
   "rank_forward_stats": {
    "basis": "forward_saved_signal",
    "population": "eod",
    "model_version": "rank4-v1",
    "n": 0,
    "unique_n": 0,
    "touch7_rate": null,
    "wilson7_lower": null,
    "avg_high_pct": null,
    "median_high_pct": null,
    "min_high_pct": null,
    "valid": false
   }
  }
 ],
 "rank_policy_name": "rank4",
 "rank_model_version": "rank4-v1",
 "rank_model_effective_from": "20260713",
 "rank_model_effective_at": "2026-07-13 09:00:00 KST",
 "rank_model_source_commit": "7f3acab"
}